{
  "project_info": {
    "project_number": "31142014468",
    "project_id": "powerlifting-application-11263",
    "storage_bucket": "powerlifting-application-11263.appspot.com"
  },
  "client": [
    {
      "client_info": {
        "mobilesdk_app_id": "1:31142014468:android:090e563b338502e67a8f51",
        "android_client_info": {
          "package_name": "com.example.flutterdatabasesalah"
        }
      },
      "oauth_client": [
        {
          "client_id": "31142014468-7km838b8ftbrl53mi3gu1bnhh45k2gsa.apps.googleusercontent.com",
          "client_type": 3
        }
      ],
      "api_key": [
        {
          "current_key": "AIzaSyBxuhQ4J4jR7yI46WLpeVPK14pLDHZeUOQ"
        }
      ],
      "services": {
        "appinvite_service": {
          "other_platform_oauth_client": [
            {
              "client_id": "31142014468-7km838b8ftbrl53mi3gu1bnhh45k2gsa.apps.googleusercontent.com",
              "client_type": 3
            }
          ]
        }
      }
    }
  ],
  "configuration_version": "1"
}